arrayops-1.0.0.dist-info/METADATA
arrayops-1.0.0.dist-info/WHEEL
arrayops/__init__.py
arrayops/_arrayops.cpython-314-darwin.so
arrayops/_arrayops.pyi
arrayops/basic.py
arrayops/elementwise.py
arrayops/iterator.py
arrayops/lazy.py
arrayops/manipulation.py
arrayops/slice.py
arrayops/stats.py
arrayops/transform.py
arrayops-1.0.0.dist-info/RECORD
