Metadata-Version: 2.4
Name: arrayops
Version: 1.0.0
Classifier: Programming Language :: Rust
Classifier: Programming Language :: Python :: Implementation :: CPython
Classifier: Programming Language :: Python :: Implementation :: PyPy
Classifier: License :: OSI Approved :: MIT License
Classifier: Development Status :: 5 - Production/Stable
Summary: Rust-backed acceleration for Python array.array
Author-email: Odos Matthews <odosmatthews@gmail.com>
Requires-Python: >=3.8
Project-URL: Homepage, https://github.com/eddiethedean/arrayops
Project-URL: Repository, https://github.com/eddiethedean/arrayops
Project-URL: Documentation, https://github.com/eddiethedean/arrayops#readme
